pps_tools/__init__.py
pps_tools/__main__.py
pps_tools/io.py
pps_tools/main.py
pps_tools/data/__init__.py
pps_tools/data/common.py
pps_tools/data/freebsd.py
pps_tools/data/linux.py
pps_tools-2.1.0.dist-info/LICENSE
pps_tools-2.1.0.dist-info/METADATA
pps_tools-2.1.0.dist-info/WHEEL
pps_tools-2.1.0.dist-info/entry_points.txt
pps_tools-2.1.0.dist-info/top_level.txt
pps_tools-2.1.0.dist-info/RECORD
