Metadata-Version: 2.1
Name: pps-tools
Version: 2.1.0
Summary: Pure Python implementation of RFC2783 PPS tools.
Author-email: "Stefan R. Filipek" <srfilipek@gmail.com>
Project-URL: Homepage, https://gitlab.com/srfilipek/pps-tools
Project-URL: Bug Tracker, https://gitlab.com/srfilipek/pps-tools/-/issues
Keywords: pps,pps-tools,ppstools,RFC2783,pulse,per,second
Classifier: Intended Audience :: Developers
Classifier: License :: OSI Approved :: MIT License
Classifier: Natural Language :: English
Classifier: Operating System :: OS Independent
Classifier: Programming Language :: Python :: 3
Classifier: Topic :: Software Development :: Libraries :: Python Modules
Classifier: Topic :: System :: Networking :: Time Synchronization
Requires-Python: >=3.5
License-File: LICENSE
Provides-Extra: dev
Requires-Dist: tox; extra == "dev"
Requires-Dist: pytest; extra == "dev"
Requires-Dist: black; extra == "dev"
Requires-Dist: isort; extra == "dev"
Requires-Dist: mypy; extra == "dev"
Requires-Dist: bumpversion; extra == "dev"
